{"videos":[{"_id":"655e1e43b498fe0018f5f836","restrictedSchedule":false,"restrictedTime":0,"teachers":["611662f47c56f70012963c39"],"urlType":"penpencilvdo","tags":[{"_id":"6480658add3d850018ef456c","name":"Ch- 23 : Determinants"}],"isFree":false,"isChatEnabled":false,"isDoubtEnabled":true,"isCommentDisabled":false,"isPathshala":false,"isDPPVideos":false,"status":"PENDING","topic":"Determinants 03 : Cramer's Rule || Introduction To Matrices || Recorded","date":"2023-11-23T00:00:00.000Z","startTime":"2023-11-23T08:00:51.000Z","endTime":"2023-11-23T08:00:00.000Z","timeline":[],"conversationId":"655e1e43b498fe0018f5f838","url":"https:\/\/d1d34p8vz63oiq.cloudfront.net\/c39d6de8-5945-40dc-9f5a-ff33d07c7b15\/master.mpd","videoDetails":{"_id":"654e0591feefd600187bd24c","id":"654e0591feefd600187bd24c","name":"Determinants 03 : Cramer's Rule || Introduction To Matrices || Recorded","image":"https:\/\/static.pw.live\/5eb393ee95fab7468a79d189\/ecdb70e5-9b39-42f0-a8bf-ed2dab7ebd81.png","videoUrl":"https:\/\/d1d34p8vz63oiq.cloudfront.net\/c39d6de8-5945-40dc-9f5a-ff33d07c7b15\/master.mpd","description":"<!DOCTYPE html>\n<html>\n<head>\n<\/head>\n<body>\n\n<\/body>\n<\/html>","duration":"02:49:09","status":"Ready","types":["DASH","HLS"],"createdAt":"2023-11-10T10:27:29.422Z","drmProtected":false},"dRoomId":"6432877c4d24040df4c9f341","isBatchDoubtEnabled":true},{"_id":"655cb9cbca04bf00186ea84d","restrictedSchedule":false,"restrictedTime":0,"teachers":["611662f47c56f70012963c39"],"urlType":"penpencilvdo","tags":[{"_id":"6480658add3d850018ef456c","name":"Ch- 23 : Determinants"}],"isFree":false,"isChatEnabled":false,"isDoubtEnabled":true,"isCommentDisabled":false,"isPathshala":false,"isDPPVideos":false,"status":"PENDING","topic":"Determinants 02 : Factor Theorem & Special Determinants || Multiplication Of Determinants || Recorded","date":"2023-11-22T00:00:00.000Z","startTime":"2023-11-22T08:00:46.000Z","endTime":"2023-11-22T08:00:04.000Z","timeline":[],"url":"https:\/\/d1d34p8vz63oiq.cloudfront.net\/81897e4b-e90f-4da7-8825-ba579b62253b\/master.mpd","videoDetails":{"_id":"654e04db5ae6070018f4f9fe","id":"654e04db5ae6070018f4f9fe","name":"Determinants 02 : Factor Theorem & Special Determinants || Multiplication Of Determinants || Recorded","image":"https:\/\/static.pw.live\/5eb393ee95fab7468a79d189\/57156dd4-8d05-43d2-a707-a20700199580.png","videoUrl":"https:\/\/d1d34p8vz63oiq.cloudfront.net\/81897e4b-e90f-4da7-8825-ba579b62253b\/master.mpd","description":"<!DOCTYPE html>\n<html>\n<head>\n<\/head>\n<body>\n\n<\/body>\n<\/html>","duration":"02:57:11","status":"Ready","types":["DASH","HLS"],"createdAt":"2023-11-10T10:24:27.073Z","drmProtected":false},"dRoomId":"6432877c4d24040df4c9f341","isBatchDoubtEnabled":true},{"_id":"655b75d5f4e1300018107136","restrictedSchedule":false,"restrictedTime":0,"teachers":["611662f47c56f70012963c39"],"urlType":"penpencilvdo","tags":[{"_id":"6480658add3d850018ef456c","name":"Ch- 23 : Determinants"}],"isFree":false,"isChatEnabled":false,"isDoubtEnabled":true,"isCommentDisabled":false,"isPathshala":false,"isDPPVideos":false,"status":"PENDING","topic":"Determinants 01 : Cofactor & Minors Of An Element || Special Determinants || NO DPP || Recorded","date":"2023-11-21T00:00:00.000Z","startTime":"2023-11-21T08:00:43.000Z","endTime":"2023-11-21T08:00:49.000Z","timeline":[],"conversationId":"655b75d5f4e1300018107138","url":"https:\/\/d1d34p8vz63oiq.cloudfront.net\/043efb17-73e6-4994-8b5b-138da0723381\/master.mpd","videoDetails":{"_id":"654ce0e3c3815b00188fcd95","id":"654ce0e3c3815b00188fcd95","name":"Determinants 01 : Cofactor & Minors Of An Element || Special Determinants || NO DPP || Recorded","image":"https:\/\/static.pw.live\/5eb393ee95fab7468a79d189\/d94e3ab4-8ed7-4c44-9028-18c54e9e8cb5.png","videoUrl":"https:\/\/d1d34p8vz63oiq.cloudfront.net\/043efb17-73e6-4994-8b5b-138da0723381\/master.mpd","description":"<!DOCTYPE html>\n<html>\n<head>\n<\/head>\n<body>\n\n<\/body>\n<\/html>","duration":"02:05:57","status":"Ready","types":["DASH","HLS"],"createdAt":"2023-11-09T13:38:43.968Z","drmProtected":false},"dRoomId":"6432877c4d24040df4c9f341","isBatchDoubtEnabled":true}],"notes":[{"_id":"6565c1cba946c1001829fead","isFree":false,"status":"PENDING","date":"2023-11-28T00:00:00.000Z","startTime":"2023-11-28T11:30:29.000Z","isDPPNotes":false,"homeworkIds":[{"_id":"6565bfa44c385a323c744b04","actions":["Open","Download","Print"],"topic":"Determinants : Handwritten Notes || Prayas JEE 2024","note":"Handwritten Notes","attachmentIds":[{"_id":"6565bfa12a53b000182798e0","name":"Determinants  Handwritten Notes  Prayas JEE 2024.pdf","baseUrl":"https:\/\/static.pw.live\/","key":"5eb393ee95fab7468a79d189\/98390f49-9913-4513-87c4-87978a58181f.pdf"}],"batchSubjectId":"63fc87eb13f7a600180c0eaa"}],"dRoomId":"6432877c4d24040df4c9f341","isBatchDoubtEnabled":true},{"_id":"655e1e43b498fe0018f5f836","isFree":false,"status":"PENDING","date":"2023-11-23T00:00:00.000Z","startTime":"2023-11-23T08:00:51.000Z","isDPPNotes":false,"homeworkIds":[{"_id":"655e233e0ac90a7d324cbae8","actions":["Open","Download","Print"],"topic":"Determinants 03 : Class Notes || Prayas JEE 2024","note":"Class Notes","attachmentIds":[{"_id":"655e233881feb70017e3c1fe","name":"Determinants 03  Class Notes  Prayas JEE 2024.pdf","baseUrl":"https:\/\/static.pw.live\/","key":"5eb393ee95fab7468a79d189\/9f3ae5ba-c285-4743-bd82-f630dca27512.pdf"}],"batchSubjectId":"63fc87eb13f7a600180c0eaa"}],"dRoomId":"6432877c4d24040df4c9f341","isBatchDoubtEnabled":true},{"_id":"655cb9cbca04bf00186ea84d","isFree":false,"status":"PENDING","date":"2023-11-22T00:00:00.000Z","startTime":"2023-11-22T08:00:46.000Z","isDPPNotes":false,"homeworkIds":[{"_id":"655d4e392b235c8695c1f672","actions":["Open","Download","Print"],"topic":"Determinants 02 : Class Notes || Prayas JEE 2024","note":"Class Notes","attachmentIds":[{"_id":"655d4e3506f18b00184800d9","name":"Determinants 02  Class Notes  Prayas JEE 2024.pdf","baseUrl":"https:\/\/static.pw.live\/","key":"5eb393ee95fab7468a79d189\/8f50e0c6-540d-44fd-939f-b918b82ca3fa.pdf"}],"batchSubjectId":"63fc87eb13f7a600180c0eaa"}],"dRoomId":"6432877c4d24040df4c9f341","isBatchDoubtEnabled":true},{"_id":"655b75d5f4e1300018107136","isFree":false,"status":"PENDING","date":"2023-11-21T00:00:00.000Z","startTime":"2023-11-21T08:00:43.000Z","isDPPNotes":false,"homeworkIds":[{"_id":"655b7d70bba83ea6ffbb0b2c","actions":["Open","Download","Print"],"topic":"Determinants 01 : Class Notes || Prayas JEE 2024","note":"Class Notes","attachmentIds":[{"_id":"655b7d6c6916a20018741e13","name":"Determinants 01  Class Notes  Prayas JEE 2024.pdf","baseUrl":"https:\/\/static.pw.live\/","key":"5eb393ee95fab7468a79d189\/9f87b839-efab-4df3-b1c8-a232c7778d3e.pdf"}],"batchSubjectId":"63fc87eb13f7a600180c0eaa"}],"dRoomId":"6432877c4d24040df4c9f341","isBatchDoubtEnabled":true}],"DppNotes":[{"_id":"655e26c4f3da0f0018e20957","isFree":false,"status":"PENDING","date":"2023-11-23T00:00:00.000Z","startTime":"2023-11-23T08:00:13.000Z","isDPPNotes":true,"homeworkIds":[{"_id":"655e26a10ac90a7d324cdbd8","actions":["Open","Download","Print"],"topic":"Determinants : DPP 02 (Of Lec 03) || Prayas JEE 2024","note":"DPP","attachmentIds":[{"_id":"655e269dc9c84000198be313","name":"Determinants  DPP 02 (Of Lec 03)  Prayas JEE 2024.pdf","baseUrl":"https:\/\/static.pw.live\/","key":"5eb393ee95fab7468a79d189\/8daacbec-e85a-4989-b23d-fddc6a775dbb.pdf"}],"batchSubjectId":"63fc87eb13f7a600180c0eaa"}],"dRoomId":"6432877c4d24040df4c9f341","isBatchDoubtEnabled":true},{"_id":"655cc17660168300187e330d","isFree":false,"status":"PENDING","date":"2023-11-22T00:00:00.000Z","startTime":"2023-11-22T08:00:38.000Z","isDPPNotes":true,"homeworkIds":[{"_id":"655cc13b2b235c8695bfce0b","actions":["Open","Download","Print"],"topic":"Determinants : DPP 01 (Of Lec 02) || Prayas JEE 2024","note":"DPP","attachmentIds":[{"_id":"655cc13688425800182e6079","name":"Determinants  DPP 01 (Of Lec 02)  Prayas JEE 2024.pdf","baseUrl":"https:\/\/static.pw.live\/","key":"5eb393ee95fab7468a79d189\/2ebbc1c7-c483-4647-95a4-cab17f6c76af.pdf"}],"batchSubjectId":"63fc87eb13f7a600180c0eaa"}],"dRoomId":"6432877c4d24040df4c9f341","isBatchDoubtEnabled":true}],"DppVideos":[],"exercises":[{"_id":"655e26c4f3da0f0018e20957","isFree":false,"status":"PENDING","date":"2023-11-23T00:00:00.000Z","startTime":"2023-11-23T08:00:13.000Z","exerciseIds":[{"type":"Exercise","availableFor":[],"status":"Active","title":"Determinants : DPP 02 MCQ Quiz","content":[{"_id":"655e282c3a73490018a50615","exerciseId":"655e282c5e9cb1b7f2568c6d","timeline":[]}],"slug":"determinants---dpp-02-mcq-quiz-686385"}],"dRoomId":"6432877c4d24040df4c9f341","isBatchDoubtEnabled":true},{"_id":"655cc17660168300187e330d","isFree":false,"status":"PENDING","date":"2023-11-22T00:00:00.000Z","startTime":"2023-11-22T08:00:38.000Z","exerciseIds":[{"type":"Exercise","availableFor":[],"status":"Active","title":"Determinants : DPP 01 MCQ Quiz","content":[{"_id":"655cc06f065fa400186b8ca3","exerciseId":"655cc06f5ac83a528cd66b40","timeline":[]}],"slug":"determinants---dpp-01-mcq-quiz-626942"}],"dRoomId":"6432877c4d24040df4c9f341","isBatchDoubtEnabled":true}]}