{"videos":[{"_id":"65354482d0e82a00186fae54","restrictedSchedule":false,"restrictedTime":0,"teachers":["64a3bbe501b0700018ddd4d8"],"urlType":"penpencilvdo","tags":[{"_id":"65354129a0566d00180734c4","name":"CH 03 : Reading Comprehension & Miscellaneous"}],"isFree":false,"isChatEnabled":false,"isDoubtEnabled":true,"isCommentDisabled":false,"isPathshala":false,"isDPPVideos":false,"status":"PENDING","topic":"Reading Comprehension & Miscellaneous (One Shot)","date":"2023-10-23T00:00:00.000Z","startTime":"2023-10-23T01:30:00.000Z","endTime":"2023-10-23T01:30:00.000Z","timeline":[],"conversationId":"6535447110526c00188ecd0a","url":"https:\/\/d1d34p8vz63oiq.cloudfront.net\/d22ee9c9-1cce-49c5-9850-c4ce3063a2d4\/master.mpd","videoDetails":{"_id":"6535e232b3df4f0018efc1f6","id":"6535e232b3df4f0018efc1f6","name":"Reading Comprehension & Miscellaneous (One Shot)","image":"https:\/\/static.pw.live\/5eb393ee95fab7468a79d189\/dcaea663-b108-4ebd-9afa-0559c3a885a6.png","videoUrl":"https:\/\/d1d34p8vz63oiq.cloudfront.net\/d22ee9c9-1cce-49c5-9850-c4ce3063a2d4\/master.mpd","description":"<!DOCTYPE html>\n<html>\n<head>\n<\/head>\n<body>\n\n<\/body>\n<\/html>","duration":"01:30:23","status":"Ready","types":["DASH","HLS"],"createdAt":"2023-10-23T03:02:10.367Z","drmProtected":false},"dRoomId":"63fc7e5a2b5f13f2231bc3a7","isBatchDoubtEnabled":true}],"notes":[{"_id":"65354482d0e82a00186fae54","isFree":false,"status":"PENDING","date":"2023-10-23T00:00:00.000Z","startTime":"2023-10-23T01:30:00.000Z","isDPPNotes":false,"homeworkIds":[{"_id":"6535ebf8b27cce0018e67f65","actions":["Open","Download","Print"],"topic":"Reading Comprehension & Miscellaneous : Class Notes","note":"Class Notes","attachmentIds":[{"_id":"6535ebf5b7a2c00018d4d9fd","name":"Reading Comprehension & Miscellaneous  Class Notes.pdf","baseUrl":"https:\/\/static.pw.live\/","key":"5eb393ee95fab7468a79d189\/1c1bf463-92c0-4ace-bb21-828ece65c9ae.pdf"}],"batchSubjectId":"652d38028713a600182d695d","solutionVideoType":"none"}],"dRoomId":"63fc7e5a2b5f13f2231bc3a7","isBatchDoubtEnabled":true}],"DppNotes":[{"_id":"6546ab0477a7e60018de1b7f","isFree":false,"status":"PENDING","date":"2023-11-05T00:00:00.000Z","startTime":"2023-11-05T10:30:00.000Z","isDPPNotes":true,"homeworkIds":[{"_id":"6546aaaa0225f40018c37159","actions":["Open","Download","Print"],"topic":"Reading Comprehension & Miscellaneous : DPP 01 Discussion Notes","note":"DPP Solution Notes","attachmentIds":[{"_id":"6546aaa9e1e3ea00188df8b3","name":"Reading Comprehension & Miscellaneous _ DPP 01 Discussion Notes.pdf","baseUrl":"https:\/\/static.pw.live\/","key":"5eb393ee95fab7468a79d189\/baabb774-e02f-49b2-86b0-2396b0a78149.pdf"}],"batchSubjectId":"652d38028713a600182d695d","solutionVideoType":"none"}],"dRoomId":"63fc7e5a2b5f13f2231bc3a7","isBatchDoubtEnabled":true},{"_id":"65460a53671d0700187604c6","isFree":false,"status":"PENDING","date":"2023-11-04T00:00:00.000Z","startTime":"2023-11-04T10:30:00.000Z","isDPPNotes":true,"homeworkIds":[{"_id":"65460755830ac50018983c7a","actions":["Open","Download","Print"],"topic":"Reading Comprehension & Miscellaneous : DPP 01","note":"DPP","attachmentIds":[{"_id":"6546075433863e0018a14eea","name":"Reading Comprehension & Miscellaneous _ DPP 01.pdf","baseUrl":"https:\/\/d2bps9p1kiy4ka.cloudfront.net\/","key":"5eb393ee95fab7468a79d189\/a284e411-4885-4c7e-95d4-f296ee073741.pdf"}],"batchSubjectId":"652d38028713a600182d695d","solutionVideoType":"none"}],"dRoomId":"63fc7e5a2b5f13f2231bc3a7","isBatchDoubtEnabled":true}],"DppVideos":[{"_id":"6546ab0477a7e60018de1b7f","restrictedSchedule":false,"restrictedTime":0,"teachers":["64a3bbe501b0700018ddd4d8"],"urlType":"penpencilvdo","tags":[{"_id":"65354129a0566d00180734c4","name":"CH 03 : Reading Comprehension & Miscellaneous"}],"isFree":false,"isChatEnabled":false,"isDoubtEnabled":false,"isCommentDisabled":false,"isPathshala":false,"isDPPVideos":true,"status":"PENDING","topic":"Reading Comprehension & Miscellaneous : DPP 01 Discussion","date":"2023-11-05T00:00:00.000Z","startTime":"2023-11-05T10:30:00.000Z","endTime":"2023-11-05T10:30:00.000Z","url":"https:\/\/d1d34p8vz63oiq.cloudfront.net\/a339af8c-da66-4724-ad1d-221418f9d2e9\/master.mpd","timeline":[],"videoDetails":{"_id":"6546a98154600c00181802b1","id":"6546a98154600c00181802b1","name":"Reading Comprehension & Miscellaneous : DPP 01 Discussion","image":"https:\/\/static.pw.live\/5eb393ee95fab7468a79d189\/40e42ef2-ff3e-4e3a-b6b3-a98fd2822f8c.png","videoUrl":"https:\/\/d1d34p8vz63oiq.cloudfront.net\/a339af8c-da66-4724-ad1d-221418f9d2e9\/master.mpd","description":"<!DOCTYPE html>\n<html>\n<head>\n<\/head>\n<body>\n\n<\/body>\n<\/html>","duration":"00:19:45","status":"Ready","types":["DASH","HLS"],"createdAt":"2023-11-04T20:28:49.120Z","drmProtected":false},"dRoomId":"63fc7e5a2b5f13f2231bc3a7","isBatchDoubtEnabled":true}],"exercises":[]}